nucleus_sdk_python/__init__.py
nucleus_sdk_python/calldata_queue.py
nucleus_sdk_python/client.py
nucleus_sdk_python/config.py
nucleus_sdk_python/exceptions.py
nucleus_sdk_python/utils.py
nucleus_sdk_python-0.1.4.dist-info/METADATA
nucleus_sdk_python-0.1.4.dist-info/WHEEL
nucleus_sdk_python-0.1.4.dist-info/RECORD
