Metadata-Version: 2.1
Name: nucleus-sdk-python
Version: 0.1.4
Summary: SDK for nucleusearn.io strategy interactions. Use Python to construct manager calls.
License: MIT
Author: Carson Case
Author-email: carson@molecularlabs.io
Requires-Python: >=3.11,<4.0
Classifier: License :: OSI Approved :: MIT License
Classifier: Programming Language :: Python :: 3
Classifier: Programming Language :: Python :: 3.11
Classifier: Programming Language :: Python :: 3.12
Classifier: Programming Language :: Python :: 3.13
Requires-Dist: eth-abi (>=5.2.0,<6.0.0)
Requires-Dist: eth-utils (>=5.2.0,<6.0.0)
Requires-Dist: pycryptodome (>=3.21.0,<4.0.0)
Requires-Dist: pytest (>=8.3.4,<9.0.0)
Requires-Dist: python-dotenv (>=1.0.1,<2.0.0)
Requires-Dist: requests (>=2.32.3,<3.0.0)
Requires-Dist: web3 (>=7.8.0,<8.0.0)
